LICENSE
README.md
setup.py
AutoAnnotate/__init__.py
AutoAnnotate/core.py
auto_ann.egg-info/PKG-INFO
auto_ann.egg-info/SOURCES.txt
auto_ann.egg-info/dependency_links.txt
auto_ann.egg-info/top_level.txt