Metadata-Version: 2.1
Name: auto-ann
Version: 0.1.5
Summary: An open-source Python library designed to label your Image datasets tailored for a given task.
Home-page: https://github.com/essamsleiman/Auto_Annotate
Author: Essam Sleiman
Author-email: essamfsleiman@gmail.com
License-File: LICENSE
